Projeto 3 - MIPS ciclo único/somador1bit.v
module somador1bit(
    output wire S,
    output wire Cout,
    input wire A,
    input wire B,
    input wire Cin
);

wire s1;
wire c1;
wire c2;

xor x1(s1, A,B);
xor x2(S,s1,Cin);

and a1(c1,A,B);
and a2(c2,Cin,s1);


or o1(Cout, c1,c2);

endmodule

Projeto 3 - MIPS ciclo único/somador8bit.v
module somador8bit(
    output [7:0] Sum,
    output Cout,
    input [7:0] A,
    input [7:0] B,
    input Cin

);

wire [6:0] cout;

somador1bit s0(.S(Sum[0]), .Cout(cout[0]), .A(A[0]), .B(B[0]), .Cin(Cin) );
somador1bit s1(.S(Sum[1]), .Cout(cout[1]), .A(A[1]), .B(B[1]), .Cin(cout[0]));
somador1bit s2(.S(Sum[2]), .Cout(cout[2]), .A(A[2]), .B(B[2]), .Cin(cout[1]));
somador1bit s3(.S(Sum[3]), .Cout(cout[3]), .A(A[3]), .B(B[3]), .Cin(cout[2]));
somador1bit s4(.S(Sum[4]), .Cout(cout[4]), .A(A[4]), .B(B[4]), .Cin(cout[3]));
somador1bit s5(.S(Sum[5]), .Cout(cout[5]), .A(A[5]), .B(B[5]), .Cin(cout[4]));
somador1bit s6(.S(Sum[6]), .Cout(cout[6]), .A(A[6]), .B(B[6]), .Cin(cout[5]));
somador1bit s7(.S(Sum[7]), .Cout(Cout), .A(A[7]), .B(B[7]), .Cin(cout[6]));


endmodule

Projeto 1 - ULA/somador32bit.v
module somador32bit(
    input [31:0] A,
    input [31:0] B,
    output [31:0] Sum,
    output Cout
);

wire [2:0] cout;


somador8bit s0(Sum[7:0], cout[0], A[7:0], B[7:0], 1'b0 );
somador8bit s1(Sum[15:8], cout[1], A[15:8], B[15:8], cout[0]);
somador8bit s2(Sum[23:16], cout[2], A[23:16], B[23:16], cout[1]);
somador8bit s3(Sum[31:24], Cout,A[31:24], B[31:24], cout[2]);

endmodule

Projeto 1 - ULA/nomes originais/ALU.v
module ALU(
    input wire [31:0] a,
    input wire[31:0] b,
    input wire [3:0] alu_ctrl,
    output reg [31:0] result,
    output wire zero,
    output reg carry_out,
    output wire overflow
    );

//Armazena o resultado do somador
wire[31:0] resultadoSomaSubtracao;

// TRATAMENTO DO SOMADOR-SUBTRATOR 
//O somador também pode servir como subtrator
//da seguinte forma:
// Soma: x = a + b
// Subtração: x = a - b = a + (-b) = a + (~b+1) 
//      representação por complemento de 2 ^^^
// -------------------------------------------

wire carry_out_pre; //carry-out sem tratamento
//FUNCIONAMENTO DO CARRY-OUT:
//soma: carry-out = carry-out-pre
//subtração: carry-out = ~carry-out-pre
// -------------------------------------------

//Tratamento de b para soma ou subtração/slt
wire[31:0] b_temp;
assign b_temp = (alu_ctrl == 4'b0110 || alu_ctrl == 4'b0111)? (~b+1'b1) : b;

// -------------------------------------------

//instância do somador (/subtrator)
somador32bit somador(a,b_temp,resultadoSomaSubtracao,carry_out_pre);

//atribuição do zero 
assign zero = (result == 32'd0) ? 1'b1 : 1'b0;

//ATRIBUIÇÃO DO OVERFLOW:
//se a soma de dois números de mesmo sinal resultar
//em um valor de sinal diferente, houve overflow
assign overflow = (a[31] == b_temp[31] && resultadoSomaSubtracao[31] != a[31]) ?  1'b1 : 1'b0;

// -------------------------------------------

//LÓGICA DE ESCOLHA
always @(*) begin
    //inicialização dos valores de saída
    result = 32'd0;
    carry_out = 1'b0;
    case(alu_ctrl)
        4'b0000: result = a & b;    //AND bit a bit  
        4'b0001: result = a | b;    //OR bit a bit
        4'b0010: begin              //Soma
            //atribuição do resultado do somador e do carry_out tratado
            result = resultadoSomaSubtracao; 
            carry_out = carry_out_pre;
        end
        4'b0110: begin              //Subtração
            //atribuição do resultado do subtrator e do carry_out tratado
            result = resultadoSomaSubtracao;
            carry_out = ~carry_out_pre;
        end

        //SLT (Set on Less than) trata com um XOR resultado da subtração
        //junto ao overflow, pois a inversão do bit de sinal do overflow 
        //pode gerar um resultado falso para números enormes
        4'b0111: result = {31'b0, resultadoSomaSubtracao[31] ^ overflow};
        4'b1100: result = ~(a ^ b); //XNOR
        default: result = 32'd0;
    endcase
end

endmodule

Projeto 1 - ULA/ALU_tb.v

`timescale 1ns/1ns

module ALU_tb;

reg signed [31:0] a,b;
reg [3:0] alu_ctrl;

wire signed [31:0] res;
wire zero, carry_out, overflow;

ALU DUT(
    a, b, alu_ctrl, res, zero, carry_out, overflow
);

initial begin
    $dumpfile("testeALU.vcd");
    $dumpvars(0, ALU_tb);

    $display("---- TESTBENCH UNIDADE LÓGICA E ARITMÉTICA MIPS ----");
    $display("             por Gustavo Gomes Tavares  ");
    $monitor("OP: %b | A:%d | B:%d | Resposta: %d |Overflow: %b| Zero: %b| Resp bin: %b", alu_ctrl, a, b, res, overflow, zero, res);
end

reg signed [32:0] expected;

initial begin
    #10;
    
    $display("Testando AND:");

    a = -32'd20;
    b =  32'd10;
    alu_ctrl = 4'b0000; //AND
    #10;

    a = 32'd7;
    b = 32'd5;
    #10;

    $display("Testando OR:");
    
    a = 32'd10;
    b = 32'd40;
    alu_ctrl = 4'b0001; //OR
    #10;

    a = 32'd9;
    b = 32'd5;
    #10;


    $display("Testando soma:");
    alu_ctrl = 4'b0010; //soma
    #10;

    a = 32'd256;
    b = 32'd256;
    #10;

    a = 32'd32768;
    b = 32'd512;
    #10;

    a = 32'd8902;
    b = 32'd0;
    #10;

    a = 32'd0;
    b = 32'd4750;
    #10;
    
    $display("Testando subtração:");

    alu_ctrl = 4'b0110; //subtração
    #10;

    $display("Testando Set on less than:");

    alu_ctrl = 4'b0111; //slt
    #10;

    $display("Testando XNOR:");
    alu_ctrl = 4'b1100; //xnor
    #10;

    $display("Edge cases (overflow):");
    a = 32'd2147483647;
    b = 32'd1;
    alu_ctrl= 4'd0010;
    #10;

    a = -32'd2147483648;
    b = 32'd1;
    alu_ctrl = 4'b0110; 
    #10;

    $display("Testando 0s:");
    a =32'd2147483647;
    b = -32'd2147483647;
    alu_ctrl= 4'd0010;
    #10;

    a = -50;
    b = -50;
    alu_ctrl = 4'b0110;
    #10;

    a = -32'd10;
    b= 32'd20;
    alu_ctrl = 4'b0111;
    #10;

    a = 32'd10;
    b = 32'd12;
    #10;

    a = 32'd12;
    b = 32'd10;
    #10;

    a = -32'd12;
    b = -32'd14;
    #10;

    $finish;
end

endmodule

Projeto 1 - ULA/testeALU.vcd
$date
	Wed Dec 17 18:21:10 2025
$end
$version
	Icarus Verilog
$end
$timescale
	1ns
$end
$scope module ALU_tb $end
$var wire 1 ! zero $end
$var wire 32 " res [31:0] $end
$var wire 1 # overflow $end
$var wire 1 $ carry_out $end
$var reg 32 % a [31:0] $end
$var reg 4 & alu_ctrl [3:0] $end
$var reg 32 ' b [31:0] $end
$scope module DUT $end
$var wire 32 ( a [31:0] $end
$var wire 4 ) alu_ctrl [3:0] $end
$var wire 32 * b [31:0] $end
$var wire 1 ! zero $end
$var wire 32 + resultadoSomaSubtracao [31:0] $end
$var wire 1 # overflow $end
$var wire 1 , carry_out_pre $end
$var wire 32 - b_temp [31:0] $end
$var reg 1 $ carry_out $end
$var reg 32 . result [31:0] $end
$scope module somador $end
$var wire 32 / A [31:0] $end
$var wire 32 0 B [31:0] $end
$var wire 3 1 cout [2:0] $end
$var wire 32 2 Sum [31:0] $end
$var wire 1 , Cout $end
$scope module s0 $end
$var wire 8 3 A [7:0] $end
$var wire 8 4 B [7:0] $end
$var wire 1 5 Cin $end
$var wire 7 6 cout [6:0] $end
$var wire 8 7 Sum [7:0] $end
$var wire 1 8 Cout $end
$scope module s0 $end
$var wire 1 9 A $end
$var wire 1 : B $end
$var wire 1 5 Cin $end
$var wire 1 ; Cout $end
$var wire 1 < S $end
$var wire 1 = c1 $end
$var wire 1 > c2 $end
$var wire 1 ? s1 $end
$upscope $end
$scope module s1 $end
$var wire 1 @ A $end
$var wire 1 A B $end
$var wire 1 B Cin $end
$var wire 1 C Cout $end
$var wire 1 D S $end
$var wire 1 E c1 $end
$var wire 1 F c2 $end
$var wire 1 G s1 $end
$upscope $end
$scope module s2 $end
$var wire 1 H A $end
$var wire 1 I B $end
$var wire 1 J Cin $end
$var wire 1 K Cout $end
$var wire 1 L S $end
$var wire 1 M c1 $end
$var wire 1 N c2 $end
$var wire 1 O s1 $end
$upscope $end
$scope module s3 $end
$var wire 1 P A $end
$var wire 1 Q B $end
$var wire 1 R Cin $end
$var wire 1 S Cout $end
$var wire 1 T S $end
$var wire 1 U c1 $end
$var wire 1 V c2 $end
$var wire 1 W s1 $end
$upscope $end
$scope module s4 $end
$var wire 1 X A $end
$var wire 1 Y B $end
$var wire 1 Z Cin $end
$var wire 1 [ Cout $end
$var wire 1 \ S $end
$var wire 1 ] c1 $end
$var wire 1 ^ c2 $end
$var wire 1 _ s1 $end
$upscope $end
$scope module s5 $end
$var wire 1 ` A $end
$var wire 1 a B $end
$var wire 1 b Cin $end
$var wire 1 c Cout $end
$var wire 1 d S $end
$var wire 1 e c1 $end
$var wire 1 f c2 $end
$var wire 1 g s1 $end
$upscope $end
$scope module s6 $end
$var wire 1 h A $end
$var wire 1 i B $end
$var wire 1 j Cin $end
$var wire 1 k Cout $end
$var wire 1 l S $end
$var wire 1 m c1 $end
$var wire 1 n c2 $end
$var wire 1 o s1 $end
$upscope $end
$scope module s7 $end
$var wire 1 p A $end
$var wire 1 q B $end
$var wire 1 r Cin $end
$var wire 1 8 Cout $end
$var wire 1 s S $end
$var wire 1 t c1 $end
$var wire 1 u c2 $end
$var wire 1 v s1 $end
$upscope $end
$upscope $end
$scope module s1 $end
$var wire 8 w A [7:0] $end
$var wire 8 x B [7:0] $end
$var wire 1 y Cin $end
$var wire 7 z cout [6:0] $end
$var wire 8 { Sum [7:0] $end
$var wire 1 | Cout $end
$scope module s0 $end
$var wire 1 } A $end
$var wire 1 ~ B $end
$var wire 1 y Cin $end
$var wire 1 !" Cout $end
$var wire 1 "" S $end
$var wire 1 #" c1 $end
$var wire 1 $" c2 $end
$var wire 1 %" s1 $end
$upscope $end
$scope module s1 $end
$var wire 1 &" A $end
$var wire 1 '" B $end
$var wire 1 (" Cin $end
$var wire 1 )" Cout $end
$var wire 1 *" S $end
$var wire 1 +" c1 $end
$var wire 1 ," c2 $end
$var wire 1 -" s1 $end
$upscope $end
$scope module s2 $end
$var wire 1 ." A $end
$var wire 1 /" B $end
$var wire 1 0" Cin $end
$var wire 1 1" Cout $end
$var wire 1 2" S $end
$var wire 1 3" c1 $end
$var wire 1 4" c2 $end
$var wire 1 5" s1 $end
$upscope $end
$scope module s3 $end
$var wire 1 6" A $end
$var wire 1 7" B $end
$var wire 1 8" Cin $end
$var wire 1 9" Cout $end
$var wire 1 :" S $end
$var wire 1 ;" c1 $end
$var wire 1 <" c2 $end
$var wire 1 =" s1 $end
$upscope $end
$scope module s4 $end
$var wire 1 >" A $end
$var wire 1 ?" B $end
$var wire 1 @" Cin $end
$var wire 1 A" Cout $end
$var wire 1 B" S $end
$var wire 1 C" c1 $end
$var wire 1 D" c2 $end
$var wire 1 E" s1 $end
$upscope $end
$scope module s5 $end
$var wire 1 F" A $end
$var wire 1 G" B $end
$var wire 1 H" Cin $end
$var wire 1 I" Cout $end
$var wire 1 J" S $end
$var wire 1 K" c1 $end
$var wire 1 L" c2 $end
$var wire 1 M" s1 $end
$upscope $end
$scope module s6 $end
$var wire 1 N" A $end
$var wire 1 O" B $end
$var wire 1 P" Cin $end
$var wire 1 Q" Cout $end
$var wire 1 R" S $end
$var wire 1 S" c1 $end
$var wire 1 T" c2 $end
$var wire 1 U" s1 $end
$upscope $end
$scope module s7 $end
$var wire 1 V" A $end
$var wire 1 W" B $end
$var wire 1 X" Cin $end
$var wire 1 | Cout $end
$var wire 1 Y" S $end
$var wire 1 Z" c1 $end
$var wire 1 [" c2 $end
$var wire 1 \" s1 $end
$upscope $end
$upscope $end
$scope module s2 $end
$var wire 8 ]" A [7:0] $end
$var wire 8 ^" B [7:0] $end
$var wire 1 _" Cin $end
$var wire 7 `" cout [6:0] $end
$var wire 8 a" Sum [7:0] $end
$var wire 1 b" Cout $end
$scope module s0 $end
$var wire 1 c" A $end
$var wire 1 d" B $end
$var wire 1 _" Cin $end
$var wire 1 e" Cout $end
$var wire 1 f" S $end
$var wire 1 g" c1 $end
$var wire 1 h" c2 $end
$var wire 1 i" s1 $end
$upscope $end
$scope module s1 $end
$var wire 1 j" A $end
$var wire 1 k" B $end
$var wire 1 l" Cin $end
$var wire 1 m" Cout $end
$var wire 1 n" S $end
$var wire 1 o" c1 $end
$var wire 1 p" c2 $end
$var wire 1 q" s1 $end
$upscope $end
$scope module s2 $end
$var wire 1 r" A $end
$var wire 1 s" B $end
$var wire 1 t" Cin $end
$var wire 1 u" Cout $end
$var wire 1 v" S $end
$var wire 1 w" c1 $end
$var wire 1 x" c2 $end
$var wire 1 y" s1 $end
$upscope $end
$scope module s3 $end
$var wire 1 z" A $end
$var wire 1 {" B $end
$var wire 1 |" Cin $end
$var wire 1 }" Cout $end
$var wire 1 ~" S $end
$var wire 1 !# c1 $end
$var wire 1 "# c2 $end
$var wire 1 ## s1 $end
$upscope $end
$scope module s4 $end
$var wire 1 $# A $end
$var wire 1 %# B $end
$var wire 1 &# Cin $end
$var wire 1 '# Cout $end
$var wire 1 (# S $end
$var wire 1 )# c1 $end
$var wire 1 *# c2 $end
$var wire 1 +# s1 $end
$upscope $end
$scope module s5 $end
$var wire 1 ,# A $end
$var wire 1 -# B $end
$var wire 1 .# Cin $end
$var wire 1 /# Cout $end
$var wire 1 0# S $end
$var wire 1 1# c1 $end
$var wire 1 2# c2 $end
$var wire 1 3# s1 $end
$upscope $end
$scope module s6 $end
$var wire 1 4# A $end
$var wire 1 5# B $end
$var wire 1 6# Cin $end
$var wire 1 7# Cout $end
$var wire 1 8# S $end
$var wire 1 9# c1 $end
$var wire 1 :# c2 $end
$var wire 1 ;# s1 $end
$upscope $end
$scope module s7 $end
$var wire 1 <# A $end
$var wire 1 =# B $end
$var wire 1 ># Cin $end
$var wire 1 b" Cout $end
$var wire 1 ?# S $end
$var wire 1 @# c1 $end
$var wire 1 A# c2 $end
$var wire 1 B# s1 $end
$upscope $end
$upscope $end
$scope module s3 $end
$var wire 8 C# A [7:0] $end
$var wire 8 D# B [7:0] $end
$var wire 1 E# Cin $end
$var wire 7 F# cout [6:0] $end
$var wire 8 G# Sum [7:0] $end
$var wire 1 , Cout $end
$scope module s0 $end
$var wire 1 H# A $end
$var wire 1 I# B $end
$var wire 1 E# Cin $end
$var wire 1 J# Cout $end
$var wire 1 K# S $end
$var wire 1 L# c1 $end
$var wire 1 M# c2 $end
$var wire 1 N# s1 $end
$upscope $end
$scope module s1 $end
$var wire 1 O# A $end
$var wire 1 P# B $end
$var wire 1 Q# Cin $end
$var wire 1 R# Cout $end
$var wire 1 S# S $end
$var wire 1 T# c1 $end
$var wire 1 U# c2 $end
$var wire 1 V# s1 $end
$upscope $end
$scope module s2 $end
$var wire 1 W# A $end
$var wire 1 X# B $end
$var wire 1 Y# Cin $end
$var wire 1 Z# Cout $end
$var wire 1 [# S $end
$var wire 1 \# c1 $end
$var wire 1 ]# c2 $end
$var wire 1 ^# s1 $end
$upscope $end
$scope module s3 $end
$var wire 1 _# A $end
$var wire 1 `# B $end
$var wire 1 a# Cin $end
$var wire 1 b# Cout $end
$var wire 1 c# S $end
$var wire 1 d# c1 $end
$var wire 1 e# c2 $end
$var wire 1 f# s1 $end
$upscope $end
$scope module s4 $end
$var wire 1 g# A $end
$var wire 1 h# B $end
$var wire 1 i# Cin $end
$var wire 1 j# Cout $end
$var wire 1 k# S $end
$var wire 1 l# c1 $end
$var wire 1 m# c2 $end
$var wire 1 n# s1 $end
$upscope $end
$scope module s5 $end
$var wire 1 o# A $end
$var wire 1 p# B $end
$var wire 1 q# Cin $end
$var wire 1 r# Cout $end
$var wire 1 s# S $end
$var wire 1 t# c1 $end
$var wire 1 u# c2 $end
$var wire 1 v# s1 $end
$upscope $end
$scope module s6 $end
$var wire 1 w# A $end
$var wire 1 x# B $end
$var wire 1 y# Cin $end
$var wire 1 z# Cout $end
$var wire 1 {# S $end
$var wire 1 |# c1 $end
$var wire 1 }# c2 $end
$var wire 1 ~# s1 $end
$upscope $end
$scope module s7 $end
$var wire 1 !$ A $end
$var wire 1 "$ B $end
$var wire 1 #$ Cin $end
$var wire 1 , Cout $end
$var wire 1 $$ S $end
$var wire 1 %$ c1 $end
$var wire 1 &$ c2 $end
$var wire 1 '$ s1 $end
$upscope $end
$upscope $end
$upscope $end
$upscope $end
$upscope $end
$enddefinitions $end
$comment Show the parameter values. $end
$dumpall
$end
#0
$dumpvars
x'$
x&$
x%$
x$$
x#$
x"$
x!$
x~#
x}#
x|#
x{#
xz#
xy#
xx#
xw#
xv#
xu#
xt#
xs#
xr#
xq#
xp#
xo#
xn#
xm#
xl#
xk#
xj#
xi#
xh#
xg#
xf#
xe#
xd#
xc#
xb#
xa#
x`#
x_#
x^#
x]#
x\#
x[#
xZ#
xY#
xX#
xW#
xV#
xU#
xT#
xS#
xR#
xQ#
xP#
xO#
xN#
xM#
xL#
xK#
xJ#
xI#
xH#
bx G#
bx F#
xE#
bx D#
bx C#
xB#
xA#
x@#
x?#
x>#
x=#
x<#
x;#
x:#
x9#
x8#
x7#
x6#
x5#
x4#
x3#
x2#
x1#
x0#
x/#
x.#
x-#
x,#
x+#
x*#
x)#
x(#
x'#
x&#
x%#
x$#
x##
x"#
x!#
x~"
x}"
x|"
x{"
xz"
xy"
xx"
xw"
xv"
xu"
xt"
xs"
xr"
xq"
xp"
xo"
xn"
xm"
xl"
xk"
xj"
xi"
xh"
xg"
xf"
xe"
xd"
xc"
xb"
bx a"
bx `"
x_"
bx ^"
bx ]"
x\"
x["
xZ"
xY"
xX"
xW"
xV"
xU"
xT"
xS"
xR"
xQ"
xP"
xO"
xN"
xM"
xL"
xK"
xJ"
xI"
xH"
xG"
xF"
xE"
xD"
xC"
xB"
xA"
x@"
x?"
x>"
x="
x<"
x;"
x:"
x9"
x8"
x7"
x6"
x5"
x4"
x3"
x2"
x1"
x0"
x/"
x."
x-"
x,"
x+"
x*"
x)"
x("
x'"
x&"
x%"
x$"
x#"
x""
x!"
x~
x}
x|
bx {
bx z
xy
bx x
bx w
xv
xu
xt
xs
xr
xq
xp
xo
xn
xm
xl
xk
xj
xi
xh
xg
xf
xe
xd
xc
xb
xa
x`
x_
x^
x]
x\
x[
xZ
xY
xX
xW
xV
xU
xT
xS
xR
xQ
xP
xO
xN
xM
xL
xK
xJ
xI
xH
xG
xF
xE
xD
xC
xB
xA
x@
x?
0>
x=
x<
x;
x:
x9
x8
bx 7
bx 6
05
bx 4
bx 3
bx 2
bx 1
bx 0
bx /
b0 .
bx -
x,
bx +
bx *
bx )
bx (
bx '
bx &
bx %
0$
x#
b0 "
1!
$end
#10
0,
1$$
0&$
0#$
0z#
1{#
0}#
0y#
0r#
1s#
0u#
0q#
0j#
1k#
0m#
0i#
0b#
1c#
0e#
0a#
0Z#
1[#
0]#
0Y#
0R#
1S#
0U#
0Q#
b0 F#
0J#
b11111111 G#
1K#
0M#
0E#
0b"
1?#
0A#
0>#
07#
18#
0:#
06#
0/#
10#
02#
0.#
0'#
1(#
0*#
0&#
0}"
1~"
0"#
0|"
0u"
1v"
0x"
0t"
0m"
1n"
0p"
0l"
b0 `"
0e"
b11111111 a"
1f"
0h"
0_"
0|
1Y"
0["
0X"
0Q"
1R"
0T"
0P"
0I"
1J"
0L"
0H"
0A"
1B"
0D"
0@"
09"
1:"
0<"
08"
01"
12"
04"
00"
0)"
1*"
0,"
0("
b0 z
0!"
b11111111 {
1""
0$"
0y
b0 1
08
1s
0u
0r
0k
1l
0n
0T
0j
0R
0c
0K
1d
0f
1L
0N
1\
0b
0J
1Z
0[
0C
0#
0<
0V
1S
0^
b11111111111111111111111111110110 +
b11111111111111111111111111110110 2
b11110110 7
1D
0F
0?
1G
1O
0M
0W
1U
0_
1g
0e
1o
0m
1v
0t
1%"
0#"
1-"
0+"
15"
03"
1="
0;"
1E"
0C"
1M"
0K"
1U"
0S"
1\"
0Z"
1i"
0g"
1q"
0o"
1y"
0w"
1##
0!#
1+#
0)#
13#
01#
1;#
09#
1B#
0@#
1N#
0L#
1V#
0T#
1^#
0\#
1f#
0d#
1n#
0l#
1v#
0t#
1~#
0|#
1'$
0%$
0B
0:
1A
0I
1Q
0Y
0a
0i
0q
0~
0'"
0/"
07"
0?"
0G"
0O"
0W"
0d"
0k"
0s"
0{"
0%#
0-#
05#
0=#
0I#
0P#
0X#
0`#
0h#
0p#
0x#
0"$
b1000 6
0;
b1010 4
b0 x
b0 ^"
b0 D#
0=
0E
0]
b1010 -
b1010 0
09
0@
1H
1P
0X
1`
1h
1p
1}
1&"
1."
16"
1>"
1F"
1N"
1V"
1c"
1j"
1r"
1z"
1$#
1,#
14#
1<#
1H#
1O#
1W#
1_#
1g#
1o#
1w#
1!$
0!
b11101100 3
b11111111 w
b11111111 ]"
b11111111 C#
b1000 "
b1000 .
b0 &
b0 )
b1010 '
b1010 *
b11111111111111111111111111101100 %
b11111111111111111111111111101100 (
b11111111111111111111111111101100 /
#20
1F
1L
1B
1R
0\
1;
1K
1J
0Z
1=
0O
1M
0#
0<
0D
1C
1T
b111 6
0S
0d
0l
b1100 7
0s
0""
0*"
02"
0:"
0B"
0J"
0R"
b0 {
0Y"
0f"
0n"
0v"
0~"
0(#
00#
08#
b0 a"
0?#
0K#
0S#
0[#
0c#
0k#
0s#
0{#
b1100 +
b1100 2
b0 G#
0$$
1:
0A
1I
0Q
0?
1G
0E
0W
0U
0g
0o
0v
0%"
0-"
05"
0="
0E"
0M"
0U"
0\"
0i"
0q"
0y"
0##
0+#
03#
0;#
0B#
0N#
0V#
0^#
0f#
0n#
0v#
0~#
0'$
b101 4
19
1@
0P
0`
0h
0p
0}
0&"
0."
06"
0>"
0F"
0N"
0V"
0c"
0j"
0r"
0z"
0$#
0,#
04#
0<#
0H#
0O#
0W#
0_#
0g#
0o#
0w#
0!$
b101 -
b101 0
b111 3
b0 w
b0 ]"
b0 C#
b101 "
b101 .
b101 '
b101 *
b111 %
b111 (
b111 /
#30
0J
0C
1\
1D
0F
1Z
1d
0B
0R
1S
1U
1g
0<
0;
0L
0N
b1000 6
0K
b110010 +
b110010 2
b110010 7
0T
0V
0:
0I
1Q
1a
0?
0=
0O
0M
0W
b101000 4
09
0H
1P
b101000 -
b101000 0
b1010 3
b101010 "
b101010 .
b1 &
b1 )
b101000 '
b101000 *
b1010 %
b1010 (
b1010 /
#40
0\
1B
0Z
1;
1L
1T
b1 6
0S
0d
1=
1O
1W
0U
0g
0<
b1110 +
b1110 2
b1110 7
1D
1:
1I
0Q
0a
0?
0G
b101 4
19
0@
b101 -
b101 0
b1001 3
b1101 "
b1101 .
b101 '
b101 *
b1001 %
b1001 (
b1001 /
#50
b1110 "
b1110 .
b10 &
b10 )
#60
0!
1*"
1("
0D
0L
b1 z
1!"
0B
0O
1#"
0<
b0 6
0;
b0 7
0T
b1000000000 +
b1000000000 2
b10 {
0""
0:
0I
1~
0?
0=
0W
0%"
b0 4
b1 x
09
0P
1}
b100000000 -
b100000000 0
b0 3
b1 w
b1000000000 "
b1000000000 .
b100000000 '
b100000000 *
b100000000 %
b100000000 (
b100000000 /
#70
0("
1-"
0""
b0 z
0!"
b1000001000000000 +
b1000001000000000 2
b10000010 {
1Y"
0~
1'"
0%"
0#"
1\"
b10 x
0}
1V"
b1000000000 -
b1000000000 0
b10000000 w
b1000001000000000 "
b1000001000000000 .
b1000000000 '
b1000000000 *
b1000000000000000 %
b1000000000000000 (
b1000000000000000 /
#80
02"
00"
1D
1L
1l
b11000110 7
1s
1*"
b0 z
0)"
1J"
b10001011000110 +
b10001011000110 2
b100010 {
0Y"
0'"
1G
1O
1o
1v
1-"
0+"
1M"
0\"
b0 x
1@
1H
1h
1p
1&"
1F"
0V"
b0 -
b0 0
b11000110 3
b100010 w
b10001011000110 "
b10001011000110 .
b0 '
b0 *
b10001011000110 %
b10001011000110 (
b10001011000110 /
#90
0!
1T
1B"
1W
1E"
1D
1L
0l
b10001110 7
1s
1*"
b1001010001110 +
b1001010001110 2
b10010 {
0J"
1A
1I
1Q
1q
1'"
1?"
1G
1O
0o
1v
1-"
0M"
b10001110 4
b10010 x
0@
0H
0h
0p
0&"
0F"
b1001010001110 -
b1001010001110 0
b0 3
b0 w
b1001010001110 "
b1001010001110 .
b1001010001110 '
b1001010001110 *
b0 %
b0 (
b0 /
#100
0L
0T
1\
1d
1l
b1110010 7
0s
1""
0*"
12"
1:"
0B"
1J"
1R"
b11101101 {
1Y"
1f"
1n"
1v"
1~"
1(#
10#
18#
b11111111 a"
1?#
1K#
1S#
1[#
1c#
1k#
1s#
1{#
b11111111111111111110110101110010 +
b11111111111111111110110101110010 2
b11111111 G#
1$$
0O
0W
1_
1g
1o
0v
1%"
0-"
15"
1="
0E"
1M"
1U"
1\"
1i"
1q"
1y"
1##
1+#
13#
1;#
1B#
1N#
1V#
1^#
1f#
1n#
1v#
1~#
1'$
0I
0Q
1Y
1a
1i
0q
1~
0'"
1/"
17"
0?"
1G"
1O"
1W"
1d"
1k"
1s"
1{"
1%#
1-#
15#
1=#
1I#
1P#
1X#
1`#
1h#
1p#
1x#
1"$
b1110010 4
b11101101 x
b11111111 ^"
b11111111 D#
b11111111111111111110110101110010 -
b11111111111111111110110101110010 0
1$
b11111111111111111110110101110010 "
b11111111111111111110110101110010 .
b110 &
b110 )
#110
0$
b1 "
b1 .
b111 &
b111 )
#120
0#
1L
1T
0\
0d
0l
b10001110 7
1s
0""
1*"
02"
0:"
1B"
0J"
0R"
b10010 {
0Y"
0f"
0n"
0v"
0~"
0(#
00#
08#
b0 a"
0?#
0K#
0S#
0[#
0c#
0k#
0s#
0{#
b1001010001110 +
b1001010001110 2
b0 G#
0$$
1O
1W
0_
0g
0o
1v
0%"
1-"
05"
0="
1E"
0M"
0U"
0\"
0i"
0q"
0y"
0##
0+#
03#
0;#
0B#
0N#
0V#
0^#
0f#
0n#
0v#
0~#
0'$
1I
1Q
0Y
0a
0i
1q
0~
1'"
0/"
07"
1?"
0G"
0O"
0W"
0d"
0k"
0s"
0{"
0%#
0-#
05#
0=#
0I#
0P#
0X#
0`#
0h#
0p#
0x#
0"$
b10001110 4
b10010 x
b0 ^"
b0 D#
b1001010001110 -
b1001010001110 0
b11111111111111111110110101110001 "
b11111111111111111110110101110001 .
b1100 &
b1100 )
#130
1#
1$$
1#$
1z#
1}#
1y#
1r#
1u#
1q#
1j#
1m#
1i#
1b#
1e#
1a#
1Z#
1]#
1Y#
1R#
1U#
1Q#
b1111111 F#
1J#
1M#
1E#
1b"
1A#
1>#
17#
1:#
16#
1/#
12#
1.#
1'#
1*#
1&#
1}"
1"#
1|"
1u"
1x"
1t"
1m"
1p"
1l"
b1111111 `"
1e"
1u
1h"
1r
1_"
1k
1|
1n
1D"
1["
1j
1@"
1X"
1c
19"
1Q"
1f
1,"
1<"
1T"
1b
1("
18"
1P"
1F
1[
1!"
11"
1I"
1B
1^
1$"
14"
1L"
1;
1N
1V
1J
1R
1Z
1y
10"
1H"
1=
0<
0D
1C
0L
1K
0T
b1111111 6
1S
0\
0d
0l
b0 7
0s
b111 1
18
0""
0*"
1)"
02"
0:"
0B"
b1111111 z
1A"
0J"
0R"
b0 {
0Y"
0f"
0n"
0v"
0~"
0(#
00#
08#
b0 a"
0?#
0K#
0S#
0[#
0c#
0k#
0s#
b10000000000000000000000000000000 +
b10000000000000000000000000000000 2
b10000000 G#
0{#
1:
0A
0I
0Q
0q
0'"
0?"
0?
1G
0E
1O
0M
1W
0U
1_
1g
1o
1v
0t
1%"
1-"
0+"
15"
1="
1E"
0C"
1M"
1U"
1\"
1i"
1q"
1y"
1##
1+#
13#
1;#
1B#
1N#
1V#
1^#
1f#
1n#
1v#
1~#
b1 4
b0 x
19
1@
1H
1P
1X
1`
1h
1p
1}
1&"
1."
16"
1>"
1F"
1N"
1V"
1c"
1j"
1r"
1z"
1$#
1,#
14#
1<#
1H#
1O#
1W#
1_#
1g#
1o#
1w#
1!
b1 -
b1 0
b11111111 3
b11111111 w
b11111111 ]"
b1111111 C#
b0 "
b0 .
b1010 &
b1010 )
b1 '
b1 *
b1111111111111111111111111111111 %
b1111111111111111111111111111111 (
b1111111111111111111111111111111 /
